ua_box_api/__init__.py
ua_box_api/ua_box_api.py
ua_box_api-2.0.0.dist-info/LICENSE
ua_box_api-2.0.0.dist-info/METADATA
ua_box_api-2.0.0.dist-info/WHEEL
ua_box_api-2.0.0.dist-info/RECORD
